luma/oled/__init__.py
luma/oled/const.py
luma/oled/device/__init__.py
luma/oled/device/color.py
luma/oled/device/framebuffer_mixin.py
luma/oled/device/greyscale.py
luma.oled-3.13.0.dist-info/LICENSE.rst
luma.oled-3.13.0.dist-info/METADATA
luma.oled-3.13.0.dist-info/WHEEL
luma.oled-3.13.0.dist-info/top_level.txt
luma.oled-3.13.0.dist-info/RECORD
