Metadata-Version: 2.1
Name: luma.oled
Version: 3.13.0
Summary: A small library to drive an OLED device with either SSD1306, SSD1309, SSD1322, SSD1325, SSD1327, SSD1331, SSD1351, SSD1362, SH1106, SH1107 or WS0010 chipset
Home-page: https://github.com/rm-hull/luma.oled
Author: Richard Hull
Author-email: richard.hull@destructuring-bind.org
License: MIT
Keywords: raspberry pi,rpi,oled,display,screen,rgb,monochrome,greyscale,color,ssd1306,ssd1309,ssd1322,ssd1325,ssd1327,ssd1331,ssd1351,sh1106,sh1107,ws0010,WEH001602A,WEG010016A,spi,i2c,parallel6800,pcf8574
Classifier: License :: OSI Approved :: MIT License
Classifier: Development Status :: 5 - Production/Stable
Classifier: Intended Audience :: Education
Classifier: Intended Audience :: Developers
Classifier: Topic :: Education
Classifier: Topic :: System :: Hardware
Classifier: Topic :: System :: Hardware :: Hardware Drivers
Classifier: Programming Language :: Python :: 3
Classifier: Programming Language :: Python :: 3.7
Classifier: Programming Language :: Python :: 3.8
Classifier: Programming Language :: Python :: 3.9
Classifier: Programming Language :: Python :: 3.10
Classifier: Programming Language :: Python :: 3.11
Requires-Python: <4,>=3.7
Provides-Extra: docs
Provides-Extra: qa
Provides-Extra: test
License-File: LICENSE.rst
